{"cameraMode":{"drawMode":0,"name":"Shaded","section":"Shading Mode"},"sceneLighting":true,"audioPlay":false,"sceneViewState":{"m_AlwaysRefresh":false,"showFog":true,"showSkybox":true,"showFlares":true,"showImageEffects":true,"showParticleSystems":true,"showVisualEffectGraphs":true,"m_FxEnabled":true},"in2DMode":false,"pivot":{"x":-2.2122724056243898,"y":-0.8798885345458984,"z":2.4541494846343996},"rotation":{"x":-0.1273728311061859,"y":0.8156211972236633,"z":-0.5299572348594666,"w":-0.19521868228912354},"size":3.0806329250335695,"orthographic":false}